CHANGELOG.md
README.md
mitol/__init__.py
mitol/google_sheets/__init__.py
mitol/google_sheets/admin.py
mitol/google_sheets/api.py
mitol/google_sheets/apps.py
mitol/google_sheets/constants.py
mitol/google_sheets/exceptions.py
mitol/google_sheets/factories.py
mitol/google_sheets/models.py
mitol/google_sheets/py.typed
mitol/google_sheets/sheet_handler_api.py
mitol/google_sheets/urls.py
mitol/google_sheets/utils.py
mitol/google_sheets/views.py
mitol/google_sheets/management/commands/__init__.py
mitol/google_sheets/migrations/0001_initial.py
mitol/google_sheets/migrations/0002_alter_filewatchrenewalattempt_sheet_type.py
mitol/google_sheets/migrations/0003_alter_pks_make_bigautos.py
mitol/google_sheets/migrations/__init__.py
mitol/google_sheets/settings/google_sheets.py
mitol_django_google_sheets-2025.6.13.dist-info/METADATA
mitol_django_google_sheets-2025.6.13.dist-info/WHEEL
mitol_django_google_sheets-2025.6.13.dist-info/RECORD
