Metadata-Version: 2.4
Name: mitol-django-google-sheets
Version: 2025.6.13
Summary: Core library to handle Google Sheets integrations in Django
License-Expression: BSD-3-Clause
Requires-Python: >=3.10
Requires-Dist: django-stubs>=1.13.1
Requires-Dist: django>=3.0
Requires-Dist: factory-boy~=3.2
Requires-Dist: google-api-python-client>=2.0
Requires-Dist: google-auth-oauthlib>=0.5.2
Requires-Dist: google-auth>=2.0
Requires-Dist: mitol-django-common
Requires-Dist: pygsheets==2.0.6
Requires-Dist: pytz>=2020.4
